raphtoryclient/__init__.py
raphtoryclient/client.py
raphtoryclient/serializers.py
raphtory_client-0.1.4.dist-info/LICENSE
raphtory_client-0.1.4.dist-info/METADATA
raphtory_client-0.1.4.dist-info/WHEEL
raphtory_client-0.1.4.dist-info/top_level.txt
raphtory_client-0.1.4.dist-info/RECORD
