Metadata-Version: 2.1
Name: raphtory-client
Version: 0.1.4
Summary: Raphtory Python Client - Temporal Graph Analytics
Home-page: https://github.com/Raphtory/Raphtory/tree/master/python
Author: Haaroon Yousaf
Author-email: haaroon.yousaf@pometry.com
License: Apache License 2.0
Keywords: raphtory pulsar raphtory-client client graph analytics temporal
Classifier: Development Status :: 4 - Beta
Classifier: License :: OSI Approved :: Apache Software License
Classifier: Operating System :: OS Independent
Classifier: Intended Audience :: Developers
Classifier: Programming Language :: Python :: 3
Classifier: Programming Language :: Python :: 3.9
Classifier: Topic :: Scientific/Engineering
Classifier: Topic :: Software Development :: Libraries
Classifier: Topic :: System :: Distributed Computing
Classifier: Topic :: Utilities
License-File: LICENSE
Requires-Dist: certifi
Requires-Dist: charset-normalizer
Requires-Dist: fastavro
Requires-Dist: idna
Requires-Dist: networkx
Requires-Dist: numpy
Requires-Dist: pandas
Requires-Dist: pulsar-client
Requires-Dist: python-dateutil
Requires-Dist: pytz
Requires-Dist: requests
Requires-Dist: six
Requires-Dist: urllib3
Requires-Dist: py4j
